ood_metrics/__init__.py
ood_metrics/metrics.py
ood_metrics/plots.py
ood_metrics/test_metrics.py
ood_metrics-1.1.2.dist-info/LICENSE
ood_metrics-1.1.2.dist-info/METADATA
ood_metrics-1.1.2.dist-info/WHEEL
ood_metrics-1.1.2.dist-info/RECORD
