Metadata-Version: 2.1
Name: ood-metrics
Version: 1.1.2
Summary: Calculate common OOD detection metrics
Home-page: https://github.com/tayden/ood-metrics
License: MIT
Keywords: OOD,out-of-distribution,anomaly,detection
Author: Taylor Denouden
Author-email: taylordenouden@gmail.com
Requires-Python: >=3.9,<3.12
Classifier: License :: OSI Approved :: MIT License
Classifier: Programming Language :: Python :: 3
Classifier: Programming Language :: Python :: 3.9
Classifier: Programming Language :: Python :: 3.10
Classifier: Programming Language :: Python :: 3.11
Requires-Dist: matplotlib (>=3.0,<4.0)
Requires-Dist: numpy (>=1.22,<2.0)
Requires-Dist: scikit-learn (>=1.0,<2.0)
Project-URL: Repository, https://github.com/tayden/ood-metrics
